Metadata-Version: 2.1
Name: thsquant
Version: 0.2.9
Summary: A short description of your awesome package
Home-page: https://github.com/qinbo23/ths-quant
Author: qinbo
Author-email: qinbo@myhexin.com
License: MIT
Platform: UNKNOWN
Classifier: Development Status :: 3 - Alpha
Classifier: Intended Audience :: Developers
Classifier: License :: OSI Approved :: MIT License
Classifier: Programming Language :: Python
Classifier: Programming Language :: Python :: 3
Classifier: Programming Language :: Python :: 3.6
Classifier: Programming Language :: Python :: 3.7
Classifier: Programming Language :: Python :: 3.8
Classifier: Programming Language :: Python :: 3.9
License-File: LICENSE.txt
Requires-Dist: safetensors (==0.3.0)
Requires-Dist: datasets (==2.10.1)
Requires-Dist: sentencepiece
Requires-Dist: accelerate (==0.17.1)
Requires-Dist: triton (==2.0.0)
Requires-Dist: texttable
Requires-Dist: toml
Requires-Dist: numpy
Requires-Dist: protobuf (==3.20.2)
Requires-Dist: gptq
